polarsteps_data_parser/__main__.py
polarsteps_data_parser/model.py
polarsteps_data_parser/pdf_generator.py
polarsteps_data_parser/retrieve_step_comments.py
polarsteps_data_parser/utils.py
polarsteps_data_parser-0.1.2.dist-info/METADATA
polarsteps_data_parser-0.1.2.dist-info/WHEEL
polarsteps_data_parser-0.1.2.dist-info/entry_points.txt
polarsteps_data_parser-0.1.2.dist-info/licenses/LICENSE
polarsteps_data_parser-0.1.2.dist-info/RECORD
