Metadata-Version: 2.4
Name: polarsteps-data-parser
Version: 0.1.2
Summary: Parse and extract data from the data export of travel tracking app Polarsteps.
Author-email: Niek van Leeuwen <ik@niekvanleeuwen.nl>
License-Expression: MIT
License-File: LICENSE
Requires-Python: ~=3.11
Requires-Dist: click<9,>=8.1.7
Requires-Dist: colorama<0.5,>=0.4.6
Requires-Dist: python-dotenv<2,>=1.0.1
Requires-Dist: reportlab<5,>=4.2.0
Requires-Dist: requests<3,>=2.32.3
Requires-Dist: tqdm<5,>=4.67.1
